brill_postaggers/__init__.py
brill_postaggers/ca_ancora-ud-brill.pkl
brill_postaggers/da_ddt-ud-brill.pkl
brill_postaggers/de_gsd-ud-brill.pkl
brill_postaggers/en_ewt-ud-brill.pkl
brill_postaggers/es_ancora-ud-brill.pkl
brill_postaggers/eu_bdt-ud-brill.pkl
brill_postaggers/fr_gsd-ud-brill.pkl
brill_postaggers/gl_ctg-ud-brill.pkl
brill_postaggers/it_vit-ud-brill.pkl
brill_postaggers/nl_alpino-ud-brill.pkl
brill_postaggers/pt_bosque-ud-brill.pkl
brill_postaggers/version.py
brill_postagger-0.1.2.dist-info/METADATA
brill_postagger-0.1.2.dist-info/WHEEL
brill_postagger-0.1.2.dist-info/top_level.txt
brill_postagger-0.1.2.dist-info/RECORD
