Metadata-Version: 2.1
Name: brill-postagger
Version: 0.1.2
Summary: Brill Postagger for various languages using NLTK
Home-page: https://github.com/TigreGotico/brill_postaggers
Author: JarbasAi
Author-email: jarbasai@mailfence.com
Classifier: Programming Language :: Python :: 3
Classifier: License :: OSI Approved :: MIT License
Classifier: Operating System :: OS Independent
Requires-Python: >=3.9
Requires-Dist: nltk
